revshellgen/__init__.py
revshellgen/main.py
revshellgen/commands/unix_bash
revshellgen/commands/unix_java
revshellgen/commands/unix_nc_mkfifo
revshellgen/commands/unix_nc_plain
revshellgen/commands/unix_perl
revshellgen/commands/unix_php
revshellgen/commands/unix_python
revshellgen/commands/unix_ruby
revshellgen/commands/unix_telnet
revshellgen/commands/windows_powershell
revshellgen-2.0.0.dist-info/licenses/LICENSE
revshellgen-2.0.0.dist-info/METADATA
revshellgen-2.0.0.dist-info/WHEEL
revshellgen-2.0.0.dist-info/entry_points.txt
revshellgen-2.0.0.dist-info/top_level.txt
revshellgen-2.0.0.dist-info/RECORD
