Metadata-Version: 2.4
Name: revshellgen
Version: 2.0.0
Summary: Reverse Shell Generator - Automate reverse shell generation with style
Author: https://github.com/t0thkr1s
Author-email: t0thkr1s <t0thkr1s@icloud.com>
License: GPL-3.0-or-later
Project-URL: Homepage, https://github.com/t0thkr1s/revshellgen
Project-URL: Repository, https://github.com/t0thkr1s/revshellgen
Project-URL: Issues, https://github.com/t0thkr1s/revshellgen/issues
Classifier: Development Status :: 5 - Production/Stable
Classifier: Intended Audience :: Information Technology
Classifier: Topic :: Security
Classifier: License :: OSI Approved :: GNU General Public License v3 (GPLv3)
Classifier: Operating System :: POSIX :: Linux
Classifier: Operating System :: MacOS
Classifier: Programming Language :: Python :: 3
Requires-Python: >=3.6
License-File: LICENSE
Requires-Dist: pyperclip>=1.8.2
Requires-Dist: colorama>=0.4.4
Requires-Dist: readchar>=3.0.4
Requires-Dist: netifaces>=0.11.0
Dynamic: author
Dynamic: license-file
